vyper_client_py/__init__.py
vyper_client_py/classes.py
vyper_client_py/client.py
vyper_client_py/exceptions.py
vyper_client_py/utils.py
vyper_client_py/websocket_client.py
vyper_client_py-0.1.5.dist-info/LICENSE
vyper_client_py-0.1.5.dist-info/METADATA
vyper_client_py-0.1.5.dist-info/WHEEL
vyper_client_py-0.1.5.dist-info/top_level.txt
vyper_client_py-0.1.5.dist-info/RECORD
