Metadata-Version: 2.1
Name: vyper-client-py
Version: 0.1.5
Summary: A Python SDK for the Vyper API
Home-page: https://github.com/Vyper-Terminal/vyper-client-py
Author: Brice Lloyd
Author-email: support@vyper.trade
Classifier: Programming Language :: Python :: 3
Classifier: License :: OSI Approved :: MIT License
Classifier: Operating System :: OS Independent
Requires-Python: >=3.6
License-File: LICENSE
Requires-Dist: requests<3,>=2.25.1
Requires-Dist: websockets<11,>=10.0
